README.md
setup.cfg
setup.py
flask_mongo_session/__init__.py
flask_mongo_session/session_processor.py
flask_mongo_session.egg-info/PKG-INFO
flask_mongo_session.egg-info/SOURCES.txt
flask_mongo_session.egg-info/dependency_links.txt
flask_mongo_session.egg-info/requires.txt
flask_mongo_session.egg-info/top_level.txt