Metadata-Version: 1.0
Name: flask-mongo-session
Version: 1.2.0
Summary: Use mongo db as session.
Home-page: https://github.com/eHanlin/flask-mongo-session
Author: Sparrow Jang
Author-email: sparrow.jang@gmail.com
License: UNKNOWN
Platform: UNKNOWN
